pen_py-0.1.3.dist-info/DESCRIPTION.rst
pen_py-0.1.3.dist-info/METADATA
pen_py-0.1.3.dist-info/RECORD
pen_py-0.1.3.dist-info/WHEEL
pen_py-0.1.3.dist-info/metadata.json
pen_py-0.1.3.dist-info/top_level.txt
penpy/__init__.py
penpy/dicplus.py
