Metadata-Version: 2.0
Name: pen-py
Version: 0.1.3
Summary: Penbox utils for python
Home-page: http://github.com/storborg/funniest
Author: Chris Castan
Author-email: chris@penbox.io
License: MIT
Platform: UNKNOWN
Classifier: Programming Language :: Python :: 3
Classifier: License :: OSI Approved :: MIT License
Classifier: Operating System :: OS Independent
Requires-Python: >=3.6
Requires-Dist: dotmap (>=1.3)
